harmonization_env/__init__.py
harmonization_env/harmonizer/__init__.py
harmonization_env/harmonizer/agent.py
harmonization_env/harmonizer/batcher.py
harmonization_env/harmonizer/enrivonment.py
harmonization_env/harmonizer/net.py
harmonization_env/harmonizer/utils/__init__.py
harmonization_env/harmonizer/utils/melody_sampler.py
harmonization_env/harmonizer/utils/music_tools.py
harmonization_env/player/MIDI_generator.py
harmonization_env/player/__init__.py
harmonization_env/player/video_generator.py
harmonization_env/resources/__init__.py
harmonization_env/resources/get_resource.py
harmonization_env/resources/mlp_test.pth
harmonization_env/voicer/__init__.py
harmonization_env/voicer/voicer.py
harmonization_env-0.1.3.dist-info/METADATA
harmonization_env-0.1.3.dist-info/WHEEL
harmonization_env-0.1.3.dist-info/top_level.txt
harmonization_env-0.1.3.dist-info/RECORD
