Metadata-Version: 2.1
Name: harmonization-env
Version: 0.1.3
Summary: Harmonization environment implementation via reinforcement learning
Author: Begotti Pietro
Author-email: pietro.begotti@studenti.unitn.it
Classifier: Programming Language :: Python :: 3
Classifier: License :: OSI Approved :: MIT License
Classifier: Operating System :: OS Independent
Requires-Python: >=3.6
Requires-Dist: torch>=2.5.1
Requires-Dist: numpy<2.1,>=1.22
Requires-Dist: midiutil>=1.2.1
Requires-Dist: midi2audio>=0.1.1
Requires-Dist: synthviz>=0.0.2
Requires-Dist: tqdm
